pypkgs_rk/.DS_Store
pypkgs_rk/__init__.py
pypkgs_rk/pypkgs_rk.py
pypkgs_rk-0.1.0.dist-info/LICENSE
pypkgs_rk-0.1.0.dist-info/WHEEL
pypkgs_rk-0.1.0.dist-info/METADATA
pypkgs_rk-0.1.0.dist-info/RECORD
